schemify.py
setup.py
schemify.egg-info/PKG-INFO
schemify.egg-info/SOURCES.txt
schemify.egg-info/dependency_links.txt
schemify.egg-info/not-zip-safe
schemify.egg-info/top_level.txt