Metadata-Version: 1.0
Name: schemify
Version: 0.1
Summary: Simple schema validation library
Home-page: UNKNOWN
Author: Andrey Popp
Author-email: 8mayday@gmail.com
License: UNKNOWN
Platform: UNKNOWN
